{"cameraMode":{"drawMode":0,"name":"Shaded","section":"Shading Mode"},"sceneLighting":true,"audioPlay":false,"sceneViewState":{"m_AlwaysRefresh":false,"showFog":true,"showSkybox":true,"showFlares":true,"showImageEffects":true,"showParticleSystems":true,"showVisualEffectGraphs":true,"m_FxEnabled":true},"in2DMode":false,"pivot":{"x":960.0,"y":540.0,"z":0.0},"rotation":{"x":0.30118539929389956,"y":-0.02059716172516346,"z":0.006512881256639957,"w":0.9533511996269226},"size":561.4248046875,"orthographic":false}